setup.py
jps_plot/__init__.py
jps_plot/jps_plot.py
jps_plot/json_utils.py
jps_plot/plot.py
jps_plot.egg-info/PKG-INFO
jps_plot.egg-info/SOURCES.txt
jps_plot.egg-info/dependency_links.txt
jps_plot.egg-info/entry_points.txt
jps_plot.egg-info/requires.txt
jps_plot.egg-info/top_level.txt