Metadata-Version: 1.0
Name: jps-plot
Version: 0.0.1a0
Summary: json plot using jps
Home-page: http://github.com/OTL/jps_plot
Author: Takashi Ogura
Author-email: t.ogura@gmail.com
License: UNKNOWN
Platform: UNKNOWN
